lmt_india_covid19_risk_assessment/__init__.py
lmt_india_covid19_risk_assessment/response.py
lmt_india_covid19_risk_assessment/survey.py
lmt_india_covid19_risk_assessment-1.0.1.dist-info/LICENSE.txt
lmt_india_covid19_risk_assessment-1.0.1.dist-info/METADATA
lmt_india_covid19_risk_assessment-1.0.1.dist-info/WHEEL
lmt_india_covid19_risk_assessment-1.0.1.dist-info/top_level.txt
lmt_india_covid19_risk_assessment-1.0.1.dist-info/RECORD
