Metadata-Version: 2.1
Name: lmt-india-covid19-risk-assessment
Version: 1.0.1
Summary: LMT-India COVID-19 Risk Assessment
Home-page: https://github.com/istresearch/lmt-india-covid19-risk-assessment
Author: IST Research
Author-email: support@istresearch.com
License: MIT License
Platform: UNKNOWN
Classifier: Programming Language :: Python :: 3.6
Classifier: Programming Language :: Python :: 3.7
Classifier: Programming Language :: Python :: 3.8
Classifier: License :: OSI Approved :: MIT License
Classifier: Operating System :: OS Independent
Requires-Dist: limesurvey-coconut (>=1.0.1)
